pruebapy/__init__.py
pruebapy/loads3.py
pruebapy-0.0.1.dist-info/METADATA
pruebapy-0.0.1.dist-info/WHEEL
pruebapy-0.0.1.dist-info/top_level.txt
pruebapy-0.0.1.dist-info/RECORD
